flake8_sarif_formatter/flake8_sarif_formatter.py
flake8_sarif_formatter-1.0.3.dist-info/licenses/LICENSE
flake8_sarif_formatter-1.0.3.dist-info/METADATA
flake8_sarif_formatter-1.0.3.dist-info/WHEEL
flake8_sarif_formatter-1.0.3.dist-info/entry_points.txt
flake8_sarif_formatter-1.0.3.dist-info/top_level.txt
flake8_sarif_formatter-1.0.3.dist-info/RECORD
