Metadata-Version: 2.4
Name: flake8-sarif-formatter
Version: 1.0.3
Summary: A SARIF formatter for flake8
License-Expression: MIT
Project-URL: Homepage, https://github.com/advanced-security/flake8-sarif-formatter
Project-URL: Bug Tracker, https://github.com/advanced-security/flake8-sarif-formatter/issues
Classifier: Framework :: Flake8
Classifier: Environment :: Console
Classifier: Intended Audience :: Developers
Classifier: Programming Language :: Python
Classifier: Programming Language :: Python :: 3
Classifier: Operating System :: OS Independent
Classifier: Topic :: Software Development :: Libraries :: Python Modules
Classifier: Topic :: Software Development :: Quality Assurance
Requires-Python: >=3.8
License-File: LICENSE
Requires-Dist: flake8>=5.0.0
Requires-Dist: requests>=2.0.0
Requires-Dist: beautifulsoup4>=4.0.0
Provides-Extra: dev
Requires-Dist: build>=1.0.0; extra == "dev"
Requires-Dist: twine>=4.0.0; extra == "dev"
Dynamic: license-file
